buildbot_fossil/__init__.py
buildbot_fossil/changes.py
buildbot_fossil/steps.py
buildbot_fossil/test/__init__.py
buildbot_fossil/test/test_changes.py
buildbot_fossil/test/test_source.py
buildbot_fossil-1.1.dist-info/entry_points.txt
buildbot_fossil-1.1.dist-info/LICENSE
buildbot_fossil-1.1.dist-info/WHEEL
buildbot_fossil-1.1.dist-info/METADATA
buildbot_fossil-1.1.dist-info/RECORD
