Metadata-Version: 2.1
Name: buildbot-fossil
Version: 1.1
Summary: Fossil version control plugin for Buildbot
Home-page: https://github.com/stoklund/buildbot-fossil
License: GPL-2.0-only
Keywords: Buildbot,Fossil SCM
Author: Jakob Stoklund Olesen
Author-email: stoklund@2pi.dk
Requires-Python: >=3.6,<4.0
Classifier: Development Status :: 5 - Production/Stable
Classifier: Intended Audience :: Developers
Classifier: License :: OSI Approved :: GNU General Public License v2 (GPLv2)
Classifier: Programming Language :: Python :: 3
Classifier: Programming Language :: Python :: 3.10
Classifier: Programming Language :: Python :: 3.6
Classifier: Programming Language :: Python :: 3.7
Classifier: Programming Language :: Python :: 3.8
Classifier: Programming Language :: Python :: 3.9
Classifier: Topic :: Software Development :: Build Tools
Classifier: Topic :: Software Development :: Testing
Requires-Dist: buildbot (>=3,<4)
Requires-Dist: treq (>=20)
Project-URL: Documentation, https://buildbot-fossil.readthedocs.io/
Project-URL: Repository, https://github.com/stoklund/buildbot-fossil
